integration_tests/__init__.py
integration_tests/acceptance.py
integration_tests/configured_catalog.json
integration_tests/invalid_config.json
integration_tests/sample_config.json
integration_tests/sample_state.json
source_talkdesk_explore/__init__.py
source_talkdesk_explore/run.py
source_talkdesk_explore/source.py
source_talkdesk_explore/spec.json
source_talkdesk_explore/streams.py
source_talkdesk_explore/talkdesk_auth.py
source_talkdesk_explore/schemas/calls.json
source_talkdesk_explore/schemas/contacts.json
source_talkdesk_explore/schemas/ring_attempts.json
source_talkdesk_explore/schemas/studio_flow_execution.json
source_talkdesk_explore/schemas/user_status.json
airbyte_source_talkdesk_explore-0.1.0.dist-info/METADATA
airbyte_source_talkdesk_explore-0.1.0.dist-info/WHEEL
airbyte_source_talkdesk_explore-0.1.0.dist-info/entry_points.txt
airbyte_source_talkdesk_explore-0.1.0.dist-info/top_level.txt
airbyte_source_talkdesk_explore-0.1.0.dist-info/RECORD
